{
  "config": {
    "precmd": [],
    "env": [],
    "path": []
  },
  "clear": {
    "targetdir": "/c/유튜브/.raw",
    "entries": [
      { "name": "@1분과학" },
      { "name": "@리뷰엉이" },
      { "name": "@보다" },
      { "name": "@빅히스토리" },
      { "name": "@석군" },
      { "name": "@쏨작가" },
      { "name": "@아재너드" },
      { "name": "@안될과학" },
      { "name": "@우주아저씨" },
      { "name": "@위니버스" },
      { "name": "@인문학이랑" },
      { "name": "@북툰" },
      { "name": "@인터스텔라" },
      { "name": "@카오스" },
      { "name": "@화학하악" },
      { "name": "@기타" },
      { "name": "보관" }
    ]
  }
}